seq_rec.vhd
-- Sequence Recognizer: VHDL Process Description
-- (See Figure 4-21 for state diagram)
library ieee;
use ieee.std_logic_1164.all;
entity seq_rec is
   port(CLK, RESET, X: in std_logic;
        Z: out std_logic);
end seq_rec;

architecture process_3 of seq_rec is
   type state_type is (A, B, C, D);
   signal state, next_state : state_type;
begin

-- Process 1 - state_register: implements positive edge-triggered
-- state storage with asynchronous reset. 
   state_register: process (CLK, RESET)
   begin
     if (RESET = '1') then
        state <= A;
     else
        if (CLK'event and ClK = '1') then
           state <= next_state;
        end if;
     end if;
end process;

-- Process 2 - next_state_function: implements next state as function
-- of input X and state. 
   next_state_func: process (X, state)
   begin
      case state is
         when A =>
	   if X = '1' then
	      next_state <= B;
	   else
	      next_state <= A;
           end if;
        when B =>
	   if X = '1' then
	      next_state <= C;
	   else
	      next_state <= A;
           end if;
        when C =>
	   if X = '1' then
	      next_state <= C;
	   else
	      next_state <= D;
           end if;
        when D =>
	   if X = '1' then
	      next_state <= B;
	   else
	      next_state <= A;
           end if;
      end case;
   end process;

-- Process 3 - output_function: implements output as function
-- of input X and state. 
   output_func: process (X, state)
   begin
      case state is
         when A =>
	    Z <= '0';
	 when B =>
	    Z <= '0';
	 when C =>
	    Z <= '0';
         when D =>
	  if X = '1' then
	     Z <= '1';
	  else
	     Z <= '0';
          end if;
      end case;
   end process;
end;

tb_seq_rec_mealy.vhd
library ieee;
use ieee.std_logic_1164.all;

-- Entidade do testbench (sem portas, pois é só para simulação)
entity tb_seq_rec_mealy is
end tb_seq_rec_mealy;

architecture test of tb_seq_rec_mealy is
    -- Declaramos o componente que vamos testar
    component seq_rec
        port (
            clk     : in  std_logic;
            reset   : in  std_logic;
            x       : in  std_logic;
            z       : out std_logic
        );
    end component;

    -- Sinais auxiliares para conectar ao componente
    signal clk     : std_logic := '0';
    signal reset   : std_logic := '1';
    signal x       : std_logic := '0';
    signal z       : std_logic;

    -- Período do clock (10 ns)
    constant clk_period : time := 10 ns;
begin
    -- Instanciação do componente a ser testado
    uut: seq_rec
        port map (
            clk   => clk,
            reset => reset,
            x     => x,
            z     => z
        );

    -- Processo que gera o clock (50% duty cycle)
    clk_process: process
    begin
        while true loop
            clk <= '0';
            wait for clk_period / 2;
            clk <= '1';
            wait for clk_period / 2;
        end loop;
    end process;

    -- Processo que aplica os estímulos (sequência de bits)
    stim_proc: process
    begin
        -- Aplicamos o reset por 20 ns
        wait for 20 ns;
        reset <= '0';

        -- Enviamos a sequência 1, 1, 0, 1 — que deve ativar a saída 'z'
        x <= '1'; wait for clk_period;
        x <= '1'; wait for clk_period;
        x <= '0'; wait for clk_period;
        x <= '1'; wait for clk_period;

        -- Enviamos algumas sequências adicionais para verificar estabilidade
        x <= '0'; wait for clk_period;
        x <= '1'; wait for clk_period;
        x <= '0'; wait for clk_period;
        x <= '1'; wait for clk_period;

        -- Encerramos a simulação
        wait for 50 ns;
        assert false report "Fim da simulação." severity failure;
    end process;

end test;

mealy.vcd
$date
  Wed Jul 23 23:24:52 2025
$end
$version
  GHDL v0
$end
$timescale
  1 fs
$end
$scope module standard $end
$upscope $end
$scope module std_logic_1164 $end
$upscope $end
$scope module tb_seq_rec_mealy $end
$var reg 1 ! clk $end
$var reg 1 " reset $end
$var reg 1 # x $end
$var reg 1 $ z $end
$scope module uut $end
$var reg 1 % clk $end
$var reg 1 & reset $end
$var reg 1 ' x $end
$var reg 1 ( z $end
$comment state is not handled $end
$comment next_state is not handled $end
$upscope $end
$upscope $end
$enddefinitions $end
#0
0!
1"
0#
0$
0%
1&
0'
0(
#5000000
1!
1%
#10000000
0!
0%
#15000000
1!
1%
#20000000
0!
0"
1#
0%
0&
1'
#25000000
1!
1%
#30000000
0!
0%
#35000000
1!
1%
#40000000
0!
0#
0%
0'
#45000000
1!
1%
#50000000
0!
1#
1$
0%
1'
1(
#55000000
1!
0$
1%
0(
#60000000
0!
0#
0%
0'
#65000000
1!
1%
#70000000
0!
1#
0%
1'
#75000000
1!
1%
#80000000
0!
0#
0%
0'
#85000000
1!
1%
#90000000
0!
1#
0%
1'
