seq_rec_moore.vhd
library ieee;
use ieee.std_logic_1164.all;

entity seq_rec_moore is
    port (
        clk     : in  std_logic;
        reset   : in  std_logic;
        x       : in  std_logic;
        z       : out std_logic
    );
end seq_rec_moore;

architecture behavior of seq_rec_moore is
    type state_type is (S0, S1, S2, S3, S4);
    signal state, next_state : state_type;
begin
    -- Process 1: Estado sequencial
    process (clk, reset)
    begin
        if reset = '1' then
            state <= S0;
        elsif rising_edge(clk) then
            state <= next_state;
        end if;
    end process;

    -- Process 2: Lógica de transição de estados
    process (state, x)
    begin
        case state is
            when S0 =>
                if x = '1' then
                    next_state <= S1;
                else
                    next_state <= S0;
                end if;
            when S1 =>
                if x = '1' then
                    next_state <= S2;
                else
                    next_state <= S0;
                end if;
            when S2 =>
                if x = '0' then
                    next_state <= S3;
                else
                    next_state <= S2;
                end if;
            when S3 =>
                if x = '1' then
                    next_state <= S4;
                else
                    next_state <= S0;
                end if;
            when S4 =>
                if x = '1' then
                    next_state <= S2;
                else
                    next_state <= S0;
                end if;
        end case;
    end process;

    -- Process 3: Lógica de saída (Moore depende do estado apenas)
    process (state)
    begin
        case state is
            when S4 =>
                z <= '1';
            when others =>
                z <= '0';
        end case;
    end process;
end behavior;

tb_seq_rec_moore.vhd
library ieee;
use ieee.std_logic_1164.all;

-- Entidade do testbench (não tem portas pois só serve para testar)
entity tb_seq_rec_moore is
end tb_seq_rec_moore;

architecture test of tb_seq_rec_moore is
    -- Declaramos o componente que vamos testar
    component seq_rec_moore
        port (
            clk     : in  std_logic;
            reset   : in  std_logic;
            x       : in  std_logic;
            z       : out std_logic
        );
    end component;

    -- Sinais internos que ligam ao DUT (Device Under Test)
    signal clk     : std_logic := '0';
    signal reset   : std_logic := '1';  -- Começamos com reset ativado
    signal x       : std_logic := '0';  -- Entrada do sistema
    signal z       : std_logic;        -- Saída do sistema

    constant clk_period : time := 10 ns;  -- Período do clock (10 ns)
begin
    -- Instanciamos o componente a ser testado
    uut: seq_rec_moore
        port map (
            clk   => clk,
            reset => reset,
            x     => x,
            z     => z
        );

    -- Processo que gera o clock (sobe e desce a cada 5 ns)
    clk_process: process
    begin
        while true loop
            clk <= '0';
            wait for clk_period / 2;
            clk <= '1';
            wait for clk_period / 2;
        end loop;
    end process;

    -- Processo de estímulo: aqui definimos os testes que serão aplicados
    stim_proc: process
    begin
        -- Mantemos o reset ativo por 20 ns e depois desativamos
        wait for 20 ns;
        reset <= '0';

        -- A partir daqui aplicamos a sequência de entrada bit a bit

        -- Enviando a sequência: 1, 1, 0, 1 → Deve ativar a saída 'z'
        x <= '1'; wait for clk_period;
        x <= '1'; wait for clk_period;
        x <= '0'; wait for clk_period;
        x <= '1'; wait for clk_period;

        -- Adicionamos algumas sequências extras para validar outras transições
        x <= '0'; wait for clk_period;
        x <= '1'; wait for clk_period;
        x <= '0'; wait for clk_period;
        x <= '1'; wait for clk_period;

        -- Encerramos a simulação com uma pausa
        wait for 50 ns;

        -- Comando que para a simulação com uma mensagem
        assert false report "Fim da simulação." severity failure;
    end process;

end test;

moore.vcd
$date
  Wed Jul 23 23:25:18 2025
$end
$version
  GHDL v0
$end
$timescale
  1 fs
$end
$scope module standard $end
$upscope $end
$scope module std_logic_1164 $end
$upscope $end
$scope module tb_seq_rec_moore $end
$var reg 1 ! clk $end
$var reg 1 " reset $end
$var reg 1 # x $end
$var reg 1 $ z $end
$scope module uut $end
$var reg 1 % clk $end
$var reg 1 & reset $end
$var reg 1 ' x $end
$var reg 1 ( z $end
$comment state is not handled $end
$comment next_state is not handled $end
$upscope $end
$upscope $end
$enddefinitions $end
#0
0!
1"
0#
0$
0%
1&
0'
0(
#5000000
1!
1%
#10000000
0!
0%
#15000000
1!
1%
#20000000
0!
0"
1#
0%
0&
1'
#25000000
1!
1%
#30000000
0!
0%
#35000000
1!
1%
#40000000
0!
0#
0%
0'
#45000000
1!
1%
#50000000
0!
1#
0%
1'
#55000000
1!
1$
1%
1(
#60000000
0!
0#
0%
0'
#65000000
1!
0$
1%
0(
#70000000
0!
1#
0%
1'
#75000000
1!
1%
#80000000
0!
0#
0%
0'
#85000000
1!
1%
#90000000
0!
1#
0%
1'
